[
  {
    "id": "tt0078632",
    "name": "San Francisco",
    "image": "http://www.sirfrancisdrake.com/images/1700-960/sir-francis-drake-hotel-downtown-san-francisco-01a2d1c1.jpg",
    "spots": [
      {
        "id": "spot-sf-1",
        "name": "Blue Bottle Coffee",
        "image": "https://lh5.googleusercontent.com/p/AF1QipO3EvosvNyNi-toQg_WJO5Jdl4LmELmCUAZxI-o=w408-h229-k-no",
        "latitude": 37.791302,
        "longitude": -122.400925,
        "prices": {
          "regular":"1.29",
          "latte":"2.25"
        }
      },
      {
        "id": "spot-sf-2",
        "name": "Mazarine Coffee",
        "image": "https://lh5.googleusercontent.com/p/AF1QipN4Lni4FrkAQrnNF21R4zKdl7NqXibUPaf7H-ki=w408-h306-k-no",
        "latitude": 37.787424,
        "longitude": -122.403839,
        "prices": {
          "regular":"3.50",
          "latte":"5.00",
          "mocha": "6.00",
          "espresso": "3.50",
          "americano": "3.50"
        }
      },
      {
        "id": "spot-sf-3",
        "name": "Four Barrel Coffee",
        "image": "https://lh5.googleusercontent.com/p/AF1QipMbsz9vYjllu3EdYzQ8Su_4sAFcR1uXF-Iq5Fkr=w408-h229-k-no",
        "latitude": 37.766721,
        "longitude": -122.421887,
        "prices": {
          "regular":"3.00",
          "latte":"4.50",
          "mocha": "5.00",
          "espresso": "3.00",
          "americano": "3.00"
        }
      },
      {
        "id": "spot-sf-4",
        "name": "Red Door Coffee",
        "image": "https://lh5.googleusercontent.com/p/AF1QipPbBF58A0AE996kuN5LPRnv5nLzXIZCVxGcjsc_=w408-h544-k-no",
        "latitude": 37.787199,
        "longitude": -122.399056,
        "prices": {
          "regular":"2.00",
          "latte":"3.75",
          "mocha": "4.75",
          "espresso": "2.50"
        }
      },
      {
        "id": "spot-sf-5",
        "name": "Workshop Cafe",
        "image": "https://lh5.googleusercontent.com/p/AF1QipNdmFSsr0XAVTqKYlrFlkMjbt45KU1oBvSkNO7q=w408-h416-k-no",
        "latitude": 37.790451,
        "longitude": -122.402383,
        "prices": {
          "regular":"2.50",
          "latte":"4.00",
          "mocha": "4.50",
          "espresso": "2.50",
          "americano": "3.00"
        }
      }
    ]

  },
  {
    "id": "tt0079531",
    "name": "Oakland",
    "image": "https://upload.wikimedia.org/wikipedia/commons/d/d5/OAKLAND%2C_CA%2C_USA_-_Skyline_and_Bridge.JPG",
    "spots": [
      {
        "id": "spot-oak-1",
        "name": "Coffee Mill",
        "image": "http://lh5.ggpht.com/-DTyDYoNtmZw/WY8hxrUou6I/AAAAAAAA1J8/ba5vAurmgts1pFCbrohP_fLJxcf1bojVACLIBGAYYCw/",
        "latitude": 37.813829,
        "longitude": -122.246847,
        "prices": {
          "regular":"2.25",
          "latte":"3.25"
        }
      },
      {
        "id": "spot-oak-2",
        "name": "Merritt Station Cafe",
        "image": "https://lh5.googleusercontent.com/p/AF1QipNCZ2BqPR_35toYBRCMiClf8-llydSn-FME9x2R=w408-h306-k-no",
        "latitude": 37.809554,
        "longitude": -122.249767,
        "prices": {
          "regular":"1.15",
          "latte":"2.50",
          "mocha":"2.50",
          "espresso":"1.50",
          "cappuccino":"2.50"
        }
      },
      {
        "id": "spot-oak-3",
        "name": "Perch Coffee House",
        "image": "https://lh5.googleusercontent.com/p/AF1QipMEyHASgy3aAqusD5j0Jgdat13Xb25cBuFFqfhz=w408-h229-k-no",
        "latitude": 37.808737,
        "longitude": -122.253075,
        "prices": {
          "regular":"2.00",
          "espresso":"2.25",
          "latte":"3.15",
          "mocha":"3.65"
        }
      },
      {
        "id": "spot-oak-4",
        "name": "Farley's East",
        "image": "http://www.farleyscoffee.com/wp-content/uploads/2014/03/interiorEastd.png",
        "latitude": 37.811076,
        "longitude": -122.266207,
        "prices": {
          "regular":"2.50",
          "latte":"4",
          "espresso":"2.50",
          "mocha":"4.50",
          "cappuccino":"3.50"
        }
      },
      {
        "id": "spot-oak-5",
        "name": "Tierra Mia",
        "image": "https://lh5.googleusercontent.com/p/AF1QipMhiW5xJjaP8KIsUgbQZKFRJXxN_0ty3VSxiRst=w408-h229-k-no",
        "latitude": 37.809178,
        "longitude": -122.268438,
        "prices": {
          "regular":"2.75",
          "latte":"2.25",
          "cappuccino":"2.95",
          "mocha":"4.75",
          "expresso":"3.75"
        }
      }
    ]
  },
  {
    "id": "tt0089672",
    "name": "Berkeley",
    "image": "https://upload.wikimedia.org/wikipedia/commons/7/7f/UCBerkeleyCampus.jpg",
    "spots": [
      {
        "id": "spot-berk-1",
        "name": "Sack's Coffee House",
        "image": "https://lh5.googleusercontent.com/p/AF1QipPJyVBWexKkWn_I77c_92ffR9J9T3CGoQriAyFs=w408-h241-k-no",
        "latitude": 37.861796,
        "longitude": -122.253316,
        "prices": {
          "regular":"1.50",
          "latte":"2.75",
          "mocha":"3.10",
          "espresso":"1.50",
          "cappuccino":"2.75"
        }
      },
      {
        "id": "spot-berk-2",
        "name": "Rasa Cafe",
        "image": "https://lh5.googleusercontent.com/p/AF1QipOY2ZqhTpGz9u2fH-IMp5ENZgdKFuoifFNIlC4h=w408-h306-k-no",
        "latitude": 37.850903,
        "longitude": -122.270861,
        "prices": {
          "regular":"2.00",
          "latte":"3.25",
          "mocha":"2.75",
          "espresso":"2.25",
          "cappuccino":"3.00"
        }
      },
      {
        "id": "spot-berk-3",
        "name": "Fertile Grounds Cafe",
        "image": "https://lh5.googleusercontent.com/p/AF1QipOAJdy3r5NKM_zkvqOQX6oFGjALVepXljCihUj2=w438-h200-k-no",
        "latitude": 37.874905,
        "longitude": -122.268853,
        "prices": {
          "regular":"1.65",
          "espresso":"1.95",
          "latte":"2.95",
          "mocha":"3.00",
          "cappuccino":"2.75",
        }
      },
      {
        "id": "spot-berk-4",
        "name": "Caffè Trieste",
        "image": "https://lh5.googleusercontent.com/p/AF1QipNMJGPr7TPGW5xWsGQ-T8HmCHR1Htuf9dlah4df=w408-h229-k-no",
        "latitude": 37.860848,
        "longitude": -122.289782,
        "prices": {
          "regular":"2.25",
          "latte":"4.00",
          "espresso":"2.50",
          "mocha":"3.00",
          "cappuccino":"4.00"
        }
      },
      {
        "id": "spot-berk-5",
        "name": "Artís Coffee",
        "image": "https://lh5.googleusercontent.com/p/AF1QipPqO1iGGIg8EEyjUwlBv0lBtTf8D6Rt5LZc9GUl=w408-h544-k-no",
        "latitude": 37.871536,
        "longitude": -122.300884,
        "prices": {
          "regular":"2.00",
          "latte":"3.75",
          "cappuccino":"3.50",
          "mocha":"4.00",
          "expresso":"2.50"
        }
      }
    ]
  },
  {
    "id": "tt0099177",
    "name": "San Leandro",
    "image": "https://upload.wikimedia.org/wikipedia/commons/f/f9/San_Leandro_Marina_07830.JPG",
    "spots": [
      {
        "id": "spot-leandro-1",
        "name": "Sabino's Coffee shop",
        "image": "https://lh5.googleusercontent.com/p/AF1QipOTIJRwcHHJBheVPBioPUL81VD58c3ytRTl6IVd=w408-h306-k-no",
        "latitude": 37.729886,
        "longitude": -122.139108,
        "prices": {
          "regular":"2.00",
          "latte":"3.15",
          "mocha":"3.40",
          "espresso":"2.30",
          "cappuccino":"2.85"
        }
      },
      {
        "id": "spot-leandro-2",
        "name": "Zocalo Coffeehouse",
        "image": "https://lh5.googleusercontent.com/p/AF1QipMeYJI20yVvwSff4Y5PmOSUw1nml01znyH6WMz9=w408-h271-k-no",
        "latitude": 37.733179,
        "longitude": -122.151008,
        "prices": {
          "regular":"2.00",
          "latte":"3.25",
          "cappuccino":"3.25"
        }
      },
      {
        "id": "spot-leandro-3",
        "name": "Tapioca Express",
        "image": "https://lh5.googleusercontent.com/p/AF1QipPfDM4PW_YFbo1WaYDbbWK25ndhvjVeXPAR69Zp=w408-h229-k-no",
        "latitude": 37.724059,
        "longitude": -122.155182,
        "prices": {
          "regular":"1.99",
          "latte":"2.99",
          "mocha":"2.99",
          "cappuccino":"2.99",
        }
      },
      {
        "id": "spot-leandro-4",
        "name": "Starbucks",
        "image": "https://lh5.googleusercontent.com/p/AF1QipPfOLWJE142WOwosJ1bB-g79MqHip5VcIMl5t5o=w408-h228-k-no",
        "latitude": 37.714586,
        "longitude": -122.141711,
        "prices": {
          "regular":"2.10",
          "latte":"2.95",
          "mocha":"3.45",
          "cappuccino":"3.75"
        }
      }
    ]
  }
]
